[
    {
        "id": 1,
        "type": "One Change",
        "departureTime": "23:24",
        "arrivalTime": "23:56",
        "totalDuration": "32 min",
        "status": "On Time",
        "live_updated_at": "23:14:34",
        "legs": [
            {
                "origin": "Streatham Common",
                "destination": "Clapham Junction Rail Station",
                "departure": "23:24",
                "arrival": "23:33",
                "arrivalPlatform_ClaphamJunction": "TBC",
                "operator": "Southern",
                "status": "On Time"
            },
            {
                "type": "transfer",
                "location": "Clapham Junction Rail Station",
                "transferTime": "19 min"
            },
            {
                "origin": "Clapham Junction Rail Station",
                "destination": "Imperial Wharf",
                "departure": "23:52",
                "arrival": "23:56",
                "departurePlatform_ClaphamJunction": "TBC",
                "operator": "Mildmay",
                "status": "On Time"
            }
        ]
    }
]